rcwa_tlv/__init__.py
rcwa_tlv/rcwa.py
rcwa_tlv/devices/device.py
rcwa_tlv/devices/normal_fields.py
rcwa_tlv/devices/shapes.py
rcwa_tlv/devices/source.py
rcwa_tlv/materials/Si.txt
rcwa_tlv/materials/SiO2.txt
rcwa_tlv/materials/TiO2.txt
rcwa_tlv/materials/__init__.py
rcwa_tlv/materials/materials.py
rcwa_tlv/utils/convmat.py
rcwa_tlv/utils/normal_vector.py
rcwa_tlv-0.0.3.dist-info/WHEEL
rcwa_tlv-0.0.3.dist-info/METADATA
rcwa_tlv-0.0.3.dist-info/RECORD
